zed/__init__.py
zed-1.1.1.dist-info/METADATA
zed-1.1.1.dist-info/WHEEL
zed-1.1.1.dist-info/top_level.txt
zed-1.1.1.dist-info/RECORD
